quantnet_controller/__init__.py
quantnet_controller/cli.py
quantnet_controller/server.py
quantnet_controller/client/__init__.py
quantnet_controller/client/client.py
quantnet_controller/common/__init__.py
quantnet_controller/common/config.py
quantnet_controller/common/exception.py
quantnet_controller/common/extra.py
quantnet_controller/common/logging.py
quantnet_controller/common/utils.py
quantnet_controller/core/__init__.py
quantnet_controller/core/calibration.py
quantnet_controller/core/calibrator.py
quantnet_controller/core/functiondispatcher.py
quantnet_controller/core/manager.py
quantnet_controller/core/messaging.py
quantnet_controller/core/node.py
quantnet_controller/core/pingpong.py
quantnet_controller/core/pingponger.py
quantnet_controller/core/scheduler.py
quantnet_controller/core/simulator.py
quantnet_controller/daemons/__init__.py
quantnet_controller/db/__init__.py
quantnet_controller/db/broker.py
quantnet_controller/db/nosql/__init__.py
quantnet_controller/db/nosql/calibration.py
quantnet_controller/db/nosql/db.py
quantnet_controller/db/nosql/layer.py
quantnet_controller/db/nosql/node.py
quantnet_controller/db/nosql/pingpong.py
quantnet_controller/db/sqla/__init__.py
quantnet_controller/db/sqla/bsmnode.py
quantnet_controller/db/sqla/calibration.py
quantnet_controller/db/sqla/constants.py
quantnet_controller/db/sqla/mnode.py
quantnet_controller/db/sqla/models.py
quantnet_controller/db/sqla/pingpong.py
quantnet_controller/db/sqla/qnode.py
quantnet_controller/db/sqla/session.py
quantnet_controller/db/sqla/switch.py
quantnet_controller/db/sqla/types.py
quantnet_controller/db/sqla/util.py
quantnet_controller/web/__init__.py
quantnet_controller/web/rest/__init__.py
quantnet_controller/web/rest/flaskapi/__init__.py
quantnet_controller/web/rest/flaskapi/v1/__init__.py
quantnet_controller/web/rest/webpy/__init__.py
quantnet_controller/web/rest/webpy/v1/__init__.py
quantnet_controller/web/ui/__init__.py
quantnet_controller/web/ui/main.py
quantnet_controller-0.0.1.dist-info/AUTHORS.rst
quantnet_controller-0.0.1.dist-info/LICENSE
quantnet_controller-0.0.1.dist-info/METADATA
quantnet_controller-0.0.1.dist-info/WHEEL
quantnet_controller-0.0.1.dist-info/entry_points.txt
quantnet_controller-0.0.1.dist-info/top_level.txt
quantnet_controller-0.0.1.dist-info/RECORD
