Metadata-Version: 2.1
Name: quantnet_controller
Version: 0.0.1
Summary: QN Server (Controller) of Quant-Net
Home-page: https://github.com/quant-net/quant-net-server
Author: Liang Zhang, Ezra Kissel
Author-email: lzhang9@es.net, kissel@es.net
License: MIT license
Keywords: quant-net controller server
Classifier: Development Status :: 2 - Pre-Alpha
Classifier: Intended Audience :: Developers
Classifier: License :: OSI Approved :: MIT License
Classifier: Natural Language :: English
Classifier: Programming Language :: Python :: 3
Classifier: Programming Language :: Python :: 3.10
Requires-Python: >=3.10
License-File: LICENSE
License-File: AUTHORS.rst
Requires-Dist: bump2version ==0.5.11
Requires-Dist: wheel ==0.33.6
Requires-Dist: watchdog ==0.9.0
Requires-Dist: flake8 >=3.7.8
Requires-Dist: tox ==3.14.0
Requires-Dist: coverage ==4.5.4
Requires-Dist: Sphinx ==1.8.5
Requires-Dist: twine ==1.14.0
Requires-Dist: Click ==8.1.3
Requires-Dist: pytest ==6.2.4
Requires-Dist: SQLAlchemy ==1.4.31
Requires-Dist: alembic ~=1.7.6
Requires-Dist: psycopg2-binary ==2.9.9
Requires-Dist: uvloop ==0.17.0
Requires-Dist: networkx
Requires-Dist: aioschedule ==0.5.2
Requires-Dist: pymongo ==3.12.3
Requires-Dist: jsonschema
